<?xml version="1.0" encoding="UTF-8"?>
<objects serializationModel="Studio.02.02.00">
	<object class="AudioFile" id="{af77b365-69e3-4565-a144-44d9f33dce38}">
		<property name="assetPath">
			<value>Phone/Effects/463344__samijoslapaho__hands-on-phone-noise2.mp3</value>
		</property>
		<property name="frequencyInKHz">
			<value>44.0999985</value>
		</property>
		<property name="channelCount">
			<value>1</value>
		</property>
		<property name="length">
			<value>3.5265306122448981</value>
		</property>
		<relationship name="masterAssetFolder">
			<destination>{015a2ab1-959b-4272-abfe-7101c5b4e3af}</destination>
		</relationship>
	</object>
</objects>
