<?xml version="1.0" encoding="UTF-8"?>
<objects serializationModel="Studio.02.02.00">
	<object class="AudioFile" id="{b57ac939-c4ca-4ba9-b33d-93ba3c2b0285}">
		<property name="assetPath">
			<value>Phone/Ringing/275163__robotjay__phone-old-landline-ringing.wav</value>
		</property>
		<property name="isStreaming">
			<value>true</value>
		</property>
		<property name="frequencyInKHz">
			<value>96</value>
		</property>
		<property name="channelCount">
			<value>2</value>
		</property>
		<property name="length">
			<value>11.330666666666668</value>
		</property>
		<relationship name="masterAssetFolder">
			<destination>{015a2ab1-959b-4272-abfe-7101c5b4e3af}</destination>
		</relationship>
	</object>
</objects>
